__init__.py
models.py
svvs_report.py
svvs_report-0.3.0.dist-info/LICENSE.txt
svvs_report-0.3.0.dist-info/METADATA
svvs_report-0.3.0.dist-info/WHEEL
svvs_report-0.3.0.dist-info/top_level.txt
svvs_report-0.3.0.dist-info/RECORD
