Metadata-Version: 2.1
Name: svvs-report
Version: 0.3.0
Summary: An application that takes a data and returns the statistic for driver.
Author-email: Seryogin Vyacheslav <vyacheslavseregin21@gmail.com>
License: Copyright (c) 2018 The Python Packaging Authority
Project-URL: Homepage, https://git.foxminded.com.ua/foxstudent102022/task-6-report-of-monaco-2018-racing/
Classifier: Programming Language :: Python :: 3
Classifier: License :: OSI Approved :: MIT License
Classifier: Operating System :: OS Independent
Requires-Python: >=3.7
License-File: LICENSE.txt
